SpecialPurpose.py
SpecialPurpose-2.dist-info/METADATA
SpecialPurpose-2.dist-info/WHEEL
SpecialPurpose-2.dist-info/top_level.txt
SpecialPurpose-2.dist-info/RECORD
